{
  "label": "唸",
  "timestamp": 1590073910939,
  "confidence": 1.0,
  "touches": [
    [
      {
        "x": 11,
        "y": 20
      },
      {
        "x": 12,
        "y": 21
      },
      {
        "x": 13,
        "y": 25
      },
      {
        "x": 14,
        "y": 28
      },
      {
        "x": 15,
        "y": 31
      },
      {
        "x": 15,
        "y": 32
      },
      {
        "x": 15,
        "y": 32
      }
    ],
    [
      {
        "x": 11,
        "y": 21
      },
      {
        "x": 11,
        "y": 21
      },
      {
        "x": 15,
        "y": 20
      },
      {
        "x": 18,
        "y": 20
      },
      {
        "x": 22,
        "y": 20
      },
      {
        "x": 24,
        "y": 20
      },
      {
        "x": 25,
        "y": 20
      },
      {
        "x": 26,
        "y": 21
      },
      {
        "x": 26,
        "y": 22
      },
      {
        "x": 26,
        "y": 26
      },
      {
        "x": 25,
        "y": 31
      },
      {
        "x": 25,
        "y": 32
      },
      {
        "x": 25,
        "y": 32
      }
    ],
    [
      {
        "x": 12,
        "y": 36
      },
      {
        "x": 12,
        "y": 36
      },
      {
        "x": 12,
        "y": 36
      },
      {
        "x": 12,
        "y": 36
      },
      {
        "x": 14,
        "y": 35
      },
      {
        "x": 18,
        "y": 34
      },
      {
        "x": 21,
        "y": 33
      },
      {
        "x": 21,
        "y": 33
      }
    ],
    [
      {
        "x": 41,
        "y": 10
      },
      {
        "x": 41,
        "y": 10
      },
      {
        "x": 40,
        "y": 10
      },
      {
        "x": 38,
        "y": 12
      },
      {
        "x": 37,
        "y": 14
      },
      {
        "x": 32,
        "y": 21
      },
      {
        "x": 29,
        "y": 25
      },
      {
        "x": 27,
        "y": 27
      },
      {
        "x": 27,
        "y": 27
      }
    ],
    [
      {
        "x": 37,
        "y": 11
      },
      {
        "x": 37,
        "y": 13
      },
      {
        "x": 38,
        "y": 14
      },
      {
        "x": 42,
        "y": 17
      },
      {
        "x": 46,
        "y": 19
      },
      {
        "x": 50,
        "y": 22
      },
      {
        "x": 53,
        "y": 23
      },
      {
        "x": 53,
        "y": 24
      },
      {
        "x": 53,
        "y": 24
      }
    ],
    [
      {
        "x": 34,
        "y": 23
      },
      {
        "x": 34,
        "y": 23
      },
      {
        "x": 36,
        "y": 23
      },
      {
        "x": 38,
        "y": 23
      },
      {
        "x": 43,
        "y": 24
      },
      {
        "x": 43,
        "y": 24
      }
    ],
    [
      {
        "x": 29,
        "y": 30
      },
      {
        "x": 29,
        "y": 30
      },
      {
        "x": 30,
        "y": 29
      },
      {
        "x": 34,
        "y": 29
      },
      {
        "x": 41,
        "y": 29
      },
      {
        "x": 46,
        "y": 29
      },
      {
        "x": 50,
        "y": 28
      },
      {
        "x": 51,
        "y": 28
      },
      {
        "x": 52,
        "y": 28
      },
      {
        "x": 53,
        "y": 28
      },
      {
        "x": 53,
        "y": 28
      },
      {
        "x": 53,
        "y": 28
      },
      {
        "x": 53,
        "y": 28
      },
      {
        "x": 53,
        "y": 28
      },
      {
        "x": 53,
        "y": 28
      },
      {
        "x": 53,
        "y": 28
      },
      {
        "x": 53,
        "y": 28
      },
      {
        "x": 53,
        "y": 28
      },
      {
        "x": 53,
        "y": 28
      },
      {
        "x": 53,
        "y": 28
      },
      {
        "x": 53,
        "y": 28
      },
      {
        "x": 53,
        "y": 28
      },
      {
        "x": 53,
        "y": 28
      },
      {
        "x": 53,
        "y": 28
      },
      {
        "x": 53,
        "y": 28
      },
      {
        "x": 53,
        "y": 28
      },
      {
        "x": 53,
        "y": 28
      },
      {
        "x": 53,
        "y": 28
      },
      {
        "x": 53,
        "y": 28
      },
      {
        "x": 52,
        "y": 29
      },
      {
        "x": 51,
        "y": 29
      },
      {
        "x": 50,
        "y": 30
      },
      {
        "x": 47,
        "y": 32
      },
      {
        "x": 44,
        "y": 35
      },
      {
        "x": 42,
        "y": 35
      },
      {
        "x": 42,
        "y": 35
      }
    ],
    [
      {
        "x": 30,
        "y": 42
      },
      {
        "x": 30,
        "y": 42
      },
      {
        "x": 29,
        "y": 43
      },
      {
        "x": 26,
        "y": 46
      },
      {
        "x": 23,
        "y": 50
      },
      {
        "x": 22,
        "y": 51
      },
      {
        "x": 22,
        "y": 51
      }
    ],
    [
      {
        "x": 33,
        "y": 42
      },
      {
        "x": 32,
        "y": 45
      },
      {
        "x": 33,
        "y": 47
      },
      {
        "x": 33,
        "y": 48
      },
      {
        "x": 35,
        "y": 51
      },
      {
        "x": 38,
        "y": 53
      },
      {
        "x": 43,
        "y": 54
      },
      {
        "x": 47,
        "y": 54
      },
      {
        "x": 48,
        "y": 54
      },
      {
        "x": 48,
        "y": 54
      }
    ],
    [
      {
        "x": 41,
        "y": 43
      },
      {
        "x": 41,
        "y": 43
      },
      {
        "x": 43,
        "y": 45
      },
      {
        "x": 48,
        "y": 46
      },
      {
        "x": 51,
        "y": 47
      },
      {
        "x": 51,
        "y": 47
      }
    ],
    [
      {
        "x": 49,
        "y": 41
      },
      {
        "x": 49,
        "y": 41
      },
      {
        "x": 49,
        "y": 41
      },
      {
        "x": 51,
        "y": 41
      },
      {
        "x": 52,
        "y": 43
      },
      {
        "x": 55,
        "y": 45
      },
      {
        "x": 58,
        "y": 47
      },
      {
        "x": 58,
        "y": 47
      }
    ]
  ],
  "image": {
    "description": "PNG image in ARGB format even though this is just a grayscale image.",
    "data": [
      "iVBORw0KGgoAAAANSUhEUgAAAEAAAABACAYAAACqaXHeAAAABHNCSVQICAgIfAhkiAAAAfxJREFU",
      "eJztWduuxCAI1JP9/1/2PDXbGKrch02dp022FZgOiNhba6O9GH9oB9A4BKAdQOMQgHYAjUMA2gE0",
      "Xk/AB+3ACmN8e7Tee4iNcgTcg85AOQJmRH35C6VrQHTwrRUnIAO9FToNPuV/pBLKKGBV8SMLYxkC",
      "ZlAkRBBRIgV2+z0VuFdawBXAaXa4pGjA7gOsBq1f7Hr/7sf127J2mgIoAjWtbu/dtUiqO0EJ617B",
      "z/Y91MAmYDZowRw8Z10qMI+0gBdBLlbbIJUWXIhSwEMFlPSfnJfa0viXehqU5r22NkigTgGLEjJO",
      "eVyIFSCV2fysZ/ArP7h2UlOAqtpomHYBTSAZwUtUplKAptrOTnmkgkd6pc8EvWqAV21xJSBjjO1t",
      "xzQP8KjCFpseNsQK2OV+ROCRAxERAYihZbS9lOOwFZG2SswEkfiZ43AUXk9A+cvRHawNEUQB9+mO",
      "94WHdK10AqQO7giyTolTCdAMQ6l3KWhJSNsGqRaWO8GVNGDSrjGFgKf+XdLXWxXwtH54CngdXnaj",
      "77lWcFMidBvcBe8xWJntUM+ubJTpA8YYaoXs3lv9H5YCWcMRK0KKoDT4yNH5DqFFUHLlfUfm2LzU",
      "cRgxYitFwAWPnYGLksdhy3W32FYrqIBMlFRAJg4BaAfQOASgHUDjEIB2AI3XE/APV3AQpq0qNxwA",
      "AAAASUVORK5CYII="
    ]
  }
}