{
  "label": "渠",
  "timestamp": 1593013116549,
  "confidence": 0.9999034404754639,
  "touches": [
    [
      {
        "x": 17,
        "y": 5
      },
      {
        "x": 17,
        "y": 5
      },
      {
        "x": 17,
        "y": 5
      },
      {
        "x": 17,
        "y": 5
      },
      {
        "x": 17,
        "y": 5
      },
      {
        "x": 18,
        "y": 6
      },
      {
        "x": 19,
        "y": 8
      },
      {
        "x": 21,
        "y": 10
      },
      {
        "x": 22,
        "y": 12
      },
      {
        "x": 23,
        "y": 13
      },
      {
        "x": 23,
        "y": 13
      }
    ],
    [
      {
        "x": 15,
        "y": 11
      },
      {
        "x": 16,
        "y": 13
      },
      {
        "x": 17,
        "y": 15
      },
      {
        "x": 18,
        "y": 17
      },
      {
        "x": 19,
        "y": 20
      },
      {
        "x": 19,
        "y": 20
      },
      {
        "x": 19,
        "y": 20
      }
    ],
    [
      {
        "x": 13,
        "y": 35
      },
      {
        "x": 13,
        "y": 35
      },
      {
        "x": 13,
        "y": 33
      },
      {
        "x": 16,
        "y": 29
      },
      {
        "x": 18,
        "y": 27
      },
      {
        "x": 19,
        "y": 26
      },
      {
        "x": 19,
        "y": 26
      }
    ],
    [
      {
        "x": 26,
        "y": 6
      },
      {
        "x": 26,
        "y": 6
      },
      {
        "x": 26,
        "y": 6
      },
      {
        "x": 28,
        "y": 6
      },
      {
        "x": 31,
        "y": 7
      },
      {
        "x": 35,
        "y": 7
      },
      {
        "x": 39,
        "y": 7
      },
      {
        "x": 44,
        "y": 7
      },
      {
        "x": 46,
        "y": 7
      },
      {
        "x": 46,
        "y": 7
      },
      {
        "x": 46,
        "y": 7
      }
    ],
    [
      {
        "x": 27,
        "y": 6
      },
      {
        "x": 27,
        "y": 6
      },
      {
        "x": 27,
        "y": 6
      },
      {
        "x": 27,
        "y": 9
      },
      {
        "x": 27,
        "y": 10
      },
      {
        "x": 27,
        "y": 14
      },
      {
        "x": 28,
        "y": 18
      },
      {
        "x": 28,
        "y": 22
      },
      {
        "x": 28,
        "y": 26
      },
      {
        "x": 28,
        "y": 28
      },
      {
        "x": 28,
        "y": 29
      },
      {
        "x": 28,
        "y": 29
      },
      {
        "x": 28,
        "y": 29
      }
    ],
    [
      {
        "x": 27,
        "y": 13
      },
      {
        "x": 27,
        "y": 13
      },
      {
        "x": 27,
        "y": 13
      },
      {
        "x": 28,
        "y": 13
      },
      {
        "x": 31,
        "y": 12
      },
      {
        "x": 36,
        "y": 12
      },
      {
        "x": 39,
        "y": 12
      },
      {
        "x": 41,
        "y": 11
      },
      {
        "x": 43,
        "y": 11
      },
      {
        "x": 45,
        "y": 11
      },
      {
        "x": 45,
        "y": 11
      },
      {
        "x": 45,
        "y": 13
      },
      {
        "x": 44,
        "y": 16
      },
      {
        "x": 44,
        "y": 18
      },
      {
        "x": 44,
        "y": 19
      },
      {
        "x": 44,
        "y": 20
      },
      {
        "x": 44,
        "y": 21
      },
      {
        "x": 44,
        "y": 21
      }
    ],
    [
      {
        "x": 28,
        "y": 20
      },
      {
        "x": 28,
        "y": 20
      },
      {
        "x": 28,
        "y": 20
      },
      {
        "x": 31,
        "y": 20
      },
      {
        "x": 34,
        "y": 20
      },
      {
        "x": 38,
        "y": 20
      },
      {
        "x": 41,
        "y": 20
      },
      {
        "x": 42,
        "y": 20
      },
      {
        "x": 44,
        "y": 20
      },
      {
        "x": 44,
        "y": 20
      },
      {
        "x": 44,
        "y": 20
      }
    ],
    [
      {
        "x": 27,
        "y": 30
      },
      {
        "x": 27,
        "y": 30
      },
      {
        "x": 27,
        "y": 30
      },
      {
        "x": 27,
        "y": 30
      },
      {
        "x": 30,
        "y": 29
      },
      {
        "x": 31,
        "y": 29
      },
      {
        "x": 36,
        "y": 28
      },
      {
        "x": 41,
        "y": 28
      },
      {
        "x": 44,
        "y": 27
      },
      {
        "x": 47,
        "y": 27
      },
      {
        "x": 48,
        "y": 27
      },
      {
        "x": 48,
        "y": 27
      },
      {
        "x": 48,
        "y": 27
      },
      {
        "x": 48,
        "y": 27
      }
    ],
    [
      {
        "x": 12,
        "y": 40
      },
      {
        "x": 12,
        "y": 40
      },
      {
        "x": 17,
        "y": 39
      },
      {
        "x": 19,
        "y": 39
      },
      {
        "x": 29,
        "y": 38
      },
      {
        "x": 32,
        "y": 38
      },
      {
        "x": 41,
        "y": 37
      },
      {
        "x": 44,
        "y": 37
      },
      {
        "x": 45,
        "y": 37
      },
      {
        "x": 45,
        "y": 37
      },
      {
        "x": 45,
        "y": 37
      }
    ],
    [
      {
        "x": 28,
        "y": 31
      },
      {
        "x": 28,
        "y": 31
      },
      {
        "x": 28,
        "y": 32
      },
      {
        "x": 29,
        "y": 35
      },
      {
        "x": 29,
        "y": 36
      },
      {
        "x": 30,
        "y": 40
      },
      {
        "x": 30,
        "y": 44
      },
      {
        "x": 30,
        "y": 48
      },
      {
        "x": 30,
        "y": 51
      },
      {
        "x": 29,
        "y": 53
      },
      {
        "x": 29,
        "y": 53
      },
      {
        "x": 29,
        "y": 53
      }
    ],
    [
      {
        "x": 29,
        "y": 38
      },
      {
        "x": 29,
        "y": 38
      },
      {
        "x": 29,
        "y": 38
      },
      {
        "x": 27,
        "y": 40
      },
      {
        "x": 24,
        "y": 43
      },
      {
        "x": 23,
        "y": 45
      },
      {
        "x": 17,
        "y": 50
      },
      {
        "x": 16,
        "y": 51
      },
      {
        "x": 16,
        "y": 52
      },
      {
        "x": 16,
        "y": 52
      }
    ],
    [
      {
        "x": 33,
        "y": 36
      },
      {
        "x": 33,
        "y": 36
      },
      {
        "x": 33,
        "y": 36
      },
      {
        "x": 36,
        "y": 39
      },
      {
        "x": 40,
        "y": 42
      },
      {
        "x": 41,
        "y": 44
      },
      {
        "x": 46,
        "y": 47
      },
      {
        "x": 47,
        "y": 48
      },
      {
        "x": 47,
        "y": 48
      }
    ]
  ],
  "image": {
    "description": "PNG image in ARGB format even though this is just a grayscale image.",
    "data": [
      "iVBORw0KGgoAAAANSUhEUgAAAEAAAABACAYAAACqaXHeAAAABHNCSVQICAgIfAhkiAAAAeZJREFU",
      "eJztWstuxCAMtKv9/192T10hRAjY40caRupl080ygz0YAxOR0Ivxkz2AbBwBsgeQDbMAIkIiz7WR",
      "D+pFIkLMfPmsx9X/RoMJsAq0BEfEvCIEIWKIB7QDrTLzf4BEANF6FFQTABYBLbEnmaLaBEczyszf",
      "z2emuPsbI6AiybwKaIhWihC4Cd6lgoY8M3//0FBHwCzc22ez71cArBDqcUXQQtwjdUwpoHF+BAlk",
      "9JzNkPUFq7NRJed7QCOg0vK2CogJrrh+i0pCvd4DYMvgTo5r/cAjctzqAA94GOnrU+AIgHrRU5uj",
      "EA+IIO7VG4D0AywDyY4akwBa8lrSpfoBu+RXSGfsF1QCWMO+0sYobBmsRLrFtgDW2a8GdQRUa21p",
      "EVoJVoyY9FI4u4LcXgW8ZnFXhDInQyOskKniA+Y6wBMRnrElAJp4TzAjKswpsFsGzxqo/TPECfMd",
      "YBckrjAqnO4uS/QCeYrgugxqq8b+JNgzNdwEQJfMXiKkF0IzRJgkXIC+srPO/kgEpBCuZ4Mo8xrd",
      "DkGJAO0Kt/Bwbg8RIAJELlvou0LQrjBR3Ja3xGboP3SHICkQ0RL3Quk6IAKmFLCEfZWUcd8MVcfr",
      "U+AIkD2AbBwBsgeQjSNA9gCycQTIHkA2fgHjNd2tJXFqZQAAAABJRU5ErkJggg=="
    ]
  }
}
