{
  "label": "鎮",
  "timestamp": 1593009948143,
  "confidence": 0.8674315810203552,
  "touches": [
    [
      {
        "x": 17,
        "y": 4
      },
      {
        "x": 17,
        "y": 4
      },
      {
        "x": 17,
        "y": 4
      },
      {
        "x": 17,
        "y": 4
      },
      {
        "x": 17,
        "y": 4
      },
      {
        "x": 17,
        "y": 4
      },
      {
        "x": 17,
        "y": 4
      },
      {
        "x": 16,
        "y": 4
      },
      {
        "x": 15,
        "y": 5
      },
      {
        "x": 13,
        "y": 8
      },
      {
        "x": 11,
        "y": 10
      },
      {
        "x": 9,
        "y": 14
      },
      {
        "x": 8,
        "y": 15
      },
      {
        "x": 7,
        "y": 16
      },
      {
        "x": 7,
        "y": 16
      }
    ],
    [
      {
        "x": 13,
        "y": 4
      },
      {
        "x": 13,
        "y": 4
      },
      {
        "x": 13,
        "y": 4
      },
      {
        "x": 14,
        "y": 5
      },
      {
        "x": 16,
        "y": 7
      },
      {
        "x": 17,
        "y": 8
      },
      {
        "x": 19,
        "y": 11
      },
      {
        "x": 21,
        "y": 12
      },
      {
        "x": 22,
        "y": 14
      },
      {
        "x": 23,
        "y": 14
      },
      {
        "x": 23,
        "y": 14
      }
    ],
    [
      {
        "x": 5,
        "y": 20
      },
      {
        "x": 5,
        "y": 20
      },
      {
        "x": 5,
        "y": 20
      },
      {
        "x": 6,
        "y": 20
      },
      {
        "x": 9,
        "y": 19
      },
      {
        "x": 10,
        "y": 19
      },
      {
        "x": 12,
        "y": 19
      },
      {
        "x": 15,
        "y": 19
      },
      {
        "x": 17,
        "y": 18
      },
      {
        "x": 18,
        "y": 18
      },
      {
        "x": 19,
        "y": 18
      },
      {
        "x": 19,
        "y": 18
      },
      {
        "x": 19,
        "y": 18
      }
    ],
    [
      {
        "x": 14,
        "y": 21
      },
      {
        "x": 14,
        "y": 21
      },
      {
        "x": 14,
        "y": 21
      },
      {
        "x": 14,
        "y": 21
      },
      {
        "x": 14,
        "y": 21
      },
      {
        "x": 14,
        "y": 21
      },
      {
        "x": 14,
        "y": 22
      },
      {
        "x": 14,
        "y": 24
      },
      {
        "x": 14,
        "y": 25
      },
      {
        "x": 14,
        "y": 25
      },
      {
        "x": 14,
        "y": 25
      }
    ],
    [
      {
        "x": 5,
        "y": 29
      },
      {
        "x": 5,
        "y": 29
      },
      {
        "x": 5,
        "y": 29
      },
      {
        "x": 5,
        "y": 29
      },
      {
        "x": 7,
        "y": 28
      },
      {
        "x": 10,
        "y": 28
      },
      {
        "x": 13,
        "y": 27
      },
      {
        "x": 16,
        "y": 26
      },
      {
        "x": 19,
        "y": 26
      },
      {
        "x": 21,
        "y": 25
      },
      {
        "x": 21,
        "y": 25
      }
    ],
    [
      {
        "x": 13,
        "y": 19
      },
      {
        "x": 13,
        "y": 19
      },
      {
        "x": 13,
        "y": 19
      },
      {
        "x": 13,
        "y": 19
      },
      {
        "x": 13,
        "y": 20
      },
      {
        "x": 13,
        "y": 23
      },
      {
        "x": 13,
        "y": 27
      },
      {
        "x": 13,
        "y": 31
      },
      {
        "x": 13,
        "y": 36
      },
      {
        "x": 13,
        "y": 40
      },
      {
        "x": 13,
        "y": 43
      },
      {
        "x": 13,
        "y": 45
      },
      {
        "x": 13,
        "y": 45
      },
      {
        "x": 13,
        "y": 45
      }
    ],
    [
      {
        "x": 5,
        "y": 35
      },
      {
        "x": 5,
        "y": 35
      },
      {
        "x": 5,
        "y": 35
      },
      {
        "x": 6,
        "y": 36
      },
      {
        "x": 8,
        "y": 38
      },
      {
        "x": 9,
        "y": 39
      },
      {
        "x": 9,
        "y": 39
      }
    ],
    [
      {
        "x": 18,
        "y": 32
      },
      {
        "x": 18,
        "y": 32
      },
      {
        "x": 18,
        "y": 32
      },
      {
        "x": 18,
        "y": 32
      },
      {
        "x": 17,
        "y": 35
      },
      {
        "x": 17,
        "y": 37
      },
      {
        "x": 17,
        "y": 37
      }
    ],
    [
      {
        "x": 5,
        "y": 47
      },
      {
        "x": 4,
        "y": 47
      },
      {
        "x": 4,
        "y": 47
      },
      {
        "x": 4,
        "y": 47
      },
      {
        "x": 5,
        "y": 46
      },
      {
        "x": 7,
        "y": 46
      },
      {
        "x": 11,
        "y": 44
      },
      {
        "x": 13,
        "y": 43
      },
      {
        "x": 16,
        "y": 42
      },
      {
        "x": 18,
        "y": 41
      },
      {
        "x": 20,
        "y": 40
      },
      {
        "x": 22,
        "y": 40
      },
      {
        "x": 22,
        "y": 40
      },
      {
        "x": 22,
        "y": 40
      }
    ],
    [
      {
        "x": 31,
        "y": 10
      },
      {
        "x": 31,
        "y": 10
      },
      {
        "x": 31,
        "y": 10
      },
      {
        "x": 32,
        "y": 10
      },
      {
        "x": 36,
        "y": 9
      },
      {
        "x": 44,
        "y": 9
      },
      {
        "x": 49,
        "y": 9
      },
      {
        "x": 52,
        "y": 9
      },
      {
        "x": 54,
        "y": 8
      },
      {
        "x": 54,
        "y": 8
      }
    ],
    [
      {
        "x": 44,
        "y": 4
      },
      {
        "x": 44,
        "y": 4
      },
      {
        "x": 44,
        "y": 4
      },
      {
        "x": 43,
        "y": 5
      },
      {
        "x": 43,
        "y": 5
      },
      {
        "x": 43,
        "y": 7
      },
      {
        "x": 43,
        "y": 9
      },
      {
        "x": 43,
        "y": 12
      },
      {
        "x": 43,
        "y": 13
      },
      {
        "x": 43,
        "y": 13
      }
    ],
    [
      {
        "x": 30,
        "y": 15
      },
      {
        "x": 30,
        "y": 15
      },
      {
        "x": 30,
        "y": 15
      },
      {
        "x": 30,
        "y": 15
      },
      {
        "x": 31,
        "y": 18
      },
      {
        "x": 32,
        "y": 21
      },
      {
        "x": 31,
        "y": 26
      },
      {
        "x": 31,
        "y": 30
      },
      {
        "x": 31,
        "y": 32
      },
      {
        "x": 31,
        "y": 33
      },
      {
        "x": 31,
        "y": 33
      }
    ],
    [
      {
        "x": 32,
        "y": 15
      },
      {
        "x": 32,
        "y": 15
      },
      {
        "x": 32,
        "y": 15
      },
      {
        "x": 32,
        "y": 15
      },
      {
        "x": 35,
        "y": 14
      },
      {
        "x": 40,
        "y": 13
      },
      {
        "x": 45,
        "y": 13
      },
      {
        "x": 49,
        "y": 13
      },
      {
        "x": 52,
        "y": 13
      },
      {
        "x": 53,
        "y": 13
      },
      {
        "x": 54,
        "y": 13
      },
      {
        "x": 54,
        "y": 13
      },
      {
        "x": 55,
        "y": 14
      },
      {
        "x": 55,
        "y": 15
      },
      {
        "x": 55,
        "y": 19
      },
      {
        "x": 54,
        "y": 23
      },
      {
        "x": 53,
        "y": 30
      },
      {
        "x": 53,
        "y": 30
      },
      {
        "x": 53,
        "y": 30
      }
    ],
    [
      {
        "x": 34,
        "y": 19
      },
      {
        "x": 34,
        "y": 19
      },
      {
        "x": 34,
        "y": 19
      },
      {
        "x": 34,
        "y": 19
      },
      {
        "x": 36,
        "y": 19
      },
      {
        "x": 41,
        "y": 18
      },
      {
        "x": 47,
        "y": 18
      },
      {
        "x": 50,
        "y": 18
      },
      {
        "x": 51,
        "y": 18
      },
      {
        "x": 51,
        "y": 18
      }
    ],
    [
      {
        "x": 35,
        "y": 25
      },
      {
        "x": 35,
        "y": 25
      },
      {
        "x": 35,
        "y": 25
      },
      {
        "x": 35,
        "y": 25
      },
      {
        "x": 36,
        "y": 25
      },
      {
        "x": 42,
        "y": 24
      },
      {
        "x": 47,
        "y": 24
      },
      {
        "x": 49,
        "y": 24
      },
      {
        "x": 49,
        "y": 24
      }
    ],
    [
      {
        "x": 31,
        "y": 32
      },
      {
        "x": 31,
        "y": 32
      },
      {
        "x": 31,
        "y": 32
      },
      {
        "x": 31,
        "y": 32
      },
      {
        "x": 31,
        "y": 32
      },
      {
        "x": 32,
        "y": 32
      },
      {
        "x": 38,
        "y": 31
      },
      {
        "x": 42,
        "y": 31
      },
      {
        "x": 45,
        "y": 31
      },
      {
        "x": 47,
        "y": 31
      },
      {
        "x": 49,
        "y": 31
      },
      {
        "x": 49,
        "y": 31
      }
    ],
    [
      {
        "x": 29,
        "y": 38
      },
      {
        "x": 29,
        "y": 38
      },
      {
        "x": 29,
        "y": 38
      },
      {
        "x": 29,
        "y": 38
      },
      {
        "x": 29,
        "y": 38
      },
      {
        "x": 32,
        "y": 37
      },
      {
        "x": 36,
        "y": 36
      },
      {
        "x": 41,
        "y": 36
      },
      {
        "x": 46,
        "y": 36
      },
      {
        "x": 49,
        "y": 37
      },
      {
        "x": 50,
        "y": 37
      },
      {
        "x": 52,
        "y": 37
      },
      {
        "x": 54,
        "y": 37
      },
      {
        "x": 54,
        "y": 37
      },
      {
        "x": 55,
        "y": 37
      },
      {
        "x": 55,
        "y": 37
      }
    ],
    [
      {
        "x": 37,
        "y": 40
      },
      {
        "x": 37,
        "y": 40
      },
      {
        "x": 37,
        "y": 40
      },
      {
        "x": 37,
        "y": 40
      },
      {
        "x": 34,
        "y": 42
      },
      {
        "x": 32,
        "y": 43
      },
      {
        "x": 30,
        "y": 45
      },
      {
        "x": 29,
        "y": 46
      },
      {
        "x": 29,
        "y": 46
      }
    ],
    [
      {
        "x": 46,
        "y": 38
      },
      {
        "x": 47,
        "y": 39
      },
      {
        "x": 49,
        "y": 41
      },
      {
        "x": 49,
        "y": 41
      },
      {
        "x": 49,
        "y": 41
      }
    ]
  ],
  "image": {
    "description": "PNG image in ARGB format even though this is just a grayscale image.",
    "data": [
      "iVBORw0KGgoAAAANSUhEUgAAAEAAAABACAYAAACqaXHeAAAABHNCSVQICAgIfAhkiAAAAiFJREFU",
      "eJztWtGOAyEIxMv9/y97D5dtNtZVkIHxrk7SpE26MoyIiFtEpMoH44tNgI2PF+Db+kCtvyumlPL6",
      "fv2Oxt02CssRcHc+A1H2zAK06pdSUmb/yb4XZgHamciOBDQgSXAnEWqtr48GRQx1QC/pIRJhlIAa",
      "PupdAJ3xo6NGy1EVATPnW2c0xnsCjJ6L2AJFFuqAHtqaoNY6JZq5c4wwjQBL6K9EwmwMDzT2oaVw",
      "a1DrjDVza6EZb7gEVhJfuxxWiVlsemw8CuDJ+ivEWTlhmgSjibGT4aMAEVvZ/T+jEPXkAqug6hwQ",
      "CWYp/SbACpnIZBW9RMw5AFUS35cB2knLJL4JwE5K2aD1BDPWPfQ0mInMPAQVwJMfUBFhHcclAIK0",
      "tm6IgkmAyBp+q1I447CyC952gf/ivJbfcAlo2l9/HVsUQlnJtAfINugpadERBT0NspAZhW4BvDPI",
      "TqaPx+HoNhjb8QvDnmAWycwOUIvuLnARihQhq/af8e9GQKQII8JaO8idY9gU1Yjg7Qp54R1DfTXW",
      "XodrboE8R2LLNZxHhGlHaPYKDOpKyzrGnZPH/nId8GQU0QhBXsNNx5DFN0R6ZKxA3CZ7oYoA1GyP",
      "xtyqIXIBPeO9cdkVoelmCLHmdnJepBFAE+oo0js4L+K8HV7BLo5fMO0C/xEf/7r8EYBNgI0jAJsA",
      "G0cANgE2jgBsAmwcAdgE2DgCsAmwcQRgE2DjB08JIdECiEG/AAAAAElFTkSuQmCC"
    ]
  }
}
