{
  "label": "空",
  "timestamp": 1593042742512,
  "confidence": 2.7328848955221474E-4,
  "touches": [
    [
      {
        "x": 36,
        "y": 4
      },
      {
        "x": 36,
        "y": 4
      },
      {
        "x": 36,
        "y": 4
      },
      {
        "x": 36,
        "y": 4
      },
      {
        "x": 36,
        "y": 4
      },
      {
        "x": 35,
        "y": 6
      },
      {
        "x": 33,
        "y": 8
      },
      {
        "x": 30,
        "y": 11
      },
      {
        "x": 30,
        "y": 11
      }
    ],
    [
      {
        "x": 13,
        "y": 12
      },
      {
        "x": 13,
        "y": 12
      },
      {
        "x": 13,
        "y": 12
      },
      {
        "x": 13,
        "y": 12
      },
      {
        "x": 11,
        "y": 16
      },
      {
        "x": 9,
        "y": 24
      },
      {
        "x": 9,
        "y": 26
      },
      {
        "x": 9,
        "y": 26
      }
    ],
    [
      {
        "x": 11,
        "y": 16
      },
      {
        "x": 11,
        "y": 16
      },
      {
        "x": 12,
        "y": 16
      },
      {
        "x": 13,
        "y": 15
      },
      {
        "x": 15,
        "y": 15
      },
      {
        "x": 20,
        "y": 14
      },
      {
        "x": 26,
        "y": 13
      },
      {
        "x": 33,
        "y": 12
      },
      {
        "x": 41,
        "y": 11
      },
      {
        "x": 48,
        "y": 10
      },
      {
        "x": 52,
        "y": 9
      },
      {
        "x": 52,
        "y": 9
      },
      {
        "x": 52,
        "y": 10
      },
      {
        "x": 50,
        "y": 13
      },
      {
        "x": 48,
        "y": 17
      },
      {
        "x": 46,
        "y": 20
      },
      {
        "x": 46,
        "y": 20
      }
    ],
    [
      {
        "x": 22,
        "y": 15
      },
      {
        "x": 22,
        "y": 15
      },
      {
        "x": 22,
        "y": 15
      },
      {
        "x": 22,
        "y": 16
      },
      {
        "x": 20,
        "y": 19
      },
      {
        "x": 17,
        "y": 23
      },
      {
        "x": 15,
        "y": 26
      },
      {
        "x": 14,
        "y": 28
      },
      {
        "x": 14,
        "y": 28
      }
    ],
    [
      {
        "x": 41,
        "y": 9
      },
      {
        "x": 41,
        "y": 9
      },
      {
        "x": 39,
        "y": 10
      },
      {
        "x": 36,
        "y": 14
      },
      {
        "x": 33,
        "y": 18
      },
      {
        "x": 32,
        "y": 22
      },
      {
        "x": 32,
        "y": 23
      },
      {
        "x": 33,
        "y": 24
      },
      {
        "x": 35,
        "y": 25
      },
      {
        "x": 41,
        "y": 25
      },
      {
        "x": 45,
        "y": 24
      },
      {
        "x": 45,
        "y": 24
      }
    ],
    [
      {
        "x": 16,
        "y": 32
      },
      {
        "x": 16,
        "y": 32
      },
      {
        "x": 16,
        "y": 32
      },
      {
        "x": 18,
        "y": 32
      },
      {
        "x": 22,
        "y": 32
      },
      {
        "x": 27,
        "y": 33
      },
      {
        "x": 31,
        "y": 32
      },
      {
        "x": 37,
        "y": 32
      },
      {
        "x": 38,
        "y": 32
      },
      {
        "x": 41,
        "y": 32
      },
      {
        "x": 42,
        "y": 32
      },
      {
        "x": 43,
        "y": 33
      },
      {
        "x": 43,
        "y": 33
      }
    ],
    [
      {
        "x": 29,
        "y": 32
      },
      {
        "x": 29,
        "y": 32
      },
      {
        "x": 29,
        "y": 32
      },
      {
        "x": 29,
        "y": 32
      },
      {
        "x": 29,
        "y": 34
      },
      {
        "x": 29,
        "y": 37
      },
      {
        "x": 30,
        "y": 40
      },
      {
        "x": 30,
        "y": 41
      },
      {
        "x": 30,
        "y": 43
      },
      {
        "x": 30,
        "y": 43
      }
    ],
    [
      {
        "x": 14,
        "y": 48
      },
      {
        "x": 14,
        "y": 48
      },
      {
        "x": 14,
        "y": 48
      },
      {
        "x": 17,
        "y": 47
      },
      {
        "x": 22,
        "y": 46
      },
      {
        "x": 27,
        "y": 45
      },
      {
        "x": 31,
        "y": 44
      },
      {
        "x": 35,
        "y": 43
      },
      {
        "x": 39,
        "y": 43
      },
      {
        "x": 43,
        "y": 43
      },
      {
        "x": 48,
        "y": 43
      },
      {
        "x": 48,
        "y": 43
      }
    ]
  ],
  "image": {
    "description": "PNG image in ARGB format even though this is just a grayscale image.",
    "data": [
      "iVBORw0KGgoAAAANSUhEUgAAAEAAAABACAYAAACqaXHeAAAABHNCSVQICAgIfAhkiAAAAaVJREFU",
      "eJztmkGSwyAMBMXW/v/L7Ikqr8sxCAlajtXHHOKZAQmspIhIlRfzQwugyQBoAUdqrVLr3ooME8Bu",
      "440wAVCECOC4+qWUrc/GAyDNi4j8bn/igZ750XDO/UMTJBaAxvzdZ1aQAD6ZvzO46pQoorwKNyGz",
      "9epl5FNwWl2qHTAqfoXJVZhLwGL2bHBmJa2nyHAAZ6Ma4yPCqOPQtQk24do+MWveI7SpADRncnSG",
      "boIzF5InrL5IgKtwgzAvogxg5epTuOwAqoN7PKvbBHesktaIZ8jmHUC/zloZPgYtr6s9Ru4Nllfe",
      "O6YvQh7mSyn/vodoivgxOFP/nqU2tQO8657sHd0AntjYNJhK4BvCUU+Evg28CdKY5gEzQxHPCZIH",
      "phIgzm3vEEw7oCfmLiCtkTBjcSvWsbo3r2+CGQAtgAYLIMI4TAQIIErza2QJ0AJo0H+IiPj0gkf9",
      "MEKPwM4s3QHevyCvwC0A7WpGOQ22vw5HwzwUvSKq2SvMJfAks1fkTJAWQJMB0AJoMgBaAE0GQAug",
      "yQBoATQZAC2AJgOgBdC8PoA/agO6n70hLgUAAAAASUVORK5CYII="
    ]
  }
}
