{
  "label": "第",
  "timestamp": 1593041989961,
  "confidence": 0.17269635200500488,
  "touches": [
    [
      {
        "x": 17,
        "y": 3
      },
      {
        "x": 17,
        "y": 3
      },
      {
        "x": 17,
        "y": 3
      },
      {
        "x": 17,
        "y": 3
      },
      {
        "x": 17,
        "y": 4
      },
      {
        "x": 15,
        "y": 7
      },
      {
        "x": 13,
        "y": 10
      },
      {
        "x": 10,
        "y": 15
      },
      {
        "x": 8,
        "y": 17
      },
      {
        "x": 8,
        "y": 17
      },
      {
        "x": 8,
        "y": 17
      }
    ],
    [
      {
        "x": 14,
        "y": 9
      },
      {
        "x": 14,
        "y": 9
      },
      {
        "x": 14,
        "y": 9
      },
      {
        "x": 14,
        "y": 9
      },
      {
        "x": 14,
        "y": 9
      },
      {
        "x": 17,
        "y": 8
      },
      {
        "x": 26,
        "y": 7
      },
      {
        "x": 30,
        "y": 7
      },
      {
        "x": 32,
        "y": 7
      },
      {
        "x": 32,
        "y": 8
      },
      {
        "x": 32,
        "y": 8
      }
    ],
    [
      {
        "x": 20,
        "y": 7
      },
      {
        "x": 20,
        "y": 7
      },
      {
        "x": 20,
        "y": 7
      },
      {
        "x": 20,
        "y": 7
      },
      {
        "x": 20,
        "y": 7
      },
      {
        "x": 22,
        "y": 9
      },
      {
        "x": 23,
        "y": 11
      },
      {
        "x": 24,
        "y": 13
      },
      {
        "x": 25,
        "y": 15
      },
      {
        "x": 26,
        "y": 16
      },
      {
        "x": 26,
        "y": 16
      }
    ],
    [
      {
        "x": 44,
        "y": 3
      },
      {
        "x": 44,
        "y": 3
      },
      {
        "x": 43,
        "y": 4
      },
      {
        "x": 41,
        "y": 6
      },
      {
        "x": 39,
        "y": 10
      },
      {
        "x": 38,
        "y": 12
      },
      {
        "x": 38,
        "y": 12
      }
    ],
    [
      {
        "x": 37,
        "y": 10
      },
      {
        "x": 37,
        "y": 10
      },
      {
        "x": 38,
        "y": 10
      },
      {
        "x": 41,
        "y": 8
      },
      {
        "x": 44,
        "y": 8
      },
      {
        "x": 49,
        "y": 7
      },
      {
        "x": 54,
        "y": 6
      },
      {
        "x": 56,
        "y": 6
      },
      {
        "x": 57,
        "y": 6
      },
      {
        "x": 57,
        "y": 6
      }
    ],
    [
      {
        "x": 46,
        "y": 7
      },
      {
        "x": 46,
        "y": 7
      },
      {
        "x": 46,
        "y": 7
      },
      {
        "x": 47,
        "y": 9
      },
      {
        "x": 48,
        "y": 10
      },
      {
        "x": 49,
        "y": 11
      },
      {
        "x": 51,
        "y": 12
      },
      {
        "x": 52,
        "y": 14
      },
      {
        "x": 53,
        "y": 15
      },
      {
        "x": 53,
        "y": 15
      }
    ],
    [
      {
        "x": 14,
        "y": 22
      },
      {
        "x": 14,
        "y": 22
      },
      {
        "x": 14,
        "y": 22
      },
      {
        "x": 20,
        "y": 22
      },
      {
        "x": 27,
        "y": 21
      },
      {
        "x": 34,
        "y": 20
      },
      {
        "x": 40,
        "y": 20
      },
      {
        "x": 43,
        "y": 20
      },
      {
        "x": 44,
        "y": 20
      },
      {
        "x": 45,
        "y": 20
      },
      {
        "x": 45,
        "y": 21
      },
      {
        "x": 44,
        "y": 23
      },
      {
        "x": 44,
        "y": 24
      },
      {
        "x": 43,
        "y": 26
      },
      {
        "x": 42,
        "y": 27
      },
      {
        "x": 42,
        "y": 27
      }
    ],
    [
      {
        "x": 15,
        "y": 30
      },
      {
        "x": 15,
        "y": 30
      },
      {
        "x": 15,
        "y": 30
      },
      {
        "x": 18,
        "y": 30
      },
      {
        "x": 25,
        "y": 29
      },
      {
        "x": 34,
        "y": 28
      },
      {
        "x": 41,
        "y": 27
      },
      {
        "x": 44,
        "y": 27
      },
      {
        "x": 45,
        "y": 27
      },
      {
        "x": 46,
        "y": 27
      },
      {
        "x": 46,
        "y": 27
      },
      {
        "x": 46,
        "y": 27
      }
    ],
    [
      {
        "x": 15,
        "y": 29
      },
      {
        "x": 15,
        "y": 29
      },
      {
        "x": 13,
        "y": 31
      },
      {
        "x": 12,
        "y": 35
      },
      {
        "x": 11,
        "y": 37
      },
      {
        "x": 11,
        "y": 39
      },
      {
        "x": 12,
        "y": 40
      },
      {
        "x": 17,
        "y": 39
      },
      {
        "x": 26,
        "y": 38
      },
      {
        "x": 35,
        "y": 36
      },
      {
        "x": 43,
        "y": 35
      },
      {
        "x": 47,
        "y": 34
      },
      {
        "x": 48,
        "y": 34
      },
      {
        "x": 48,
        "y": 36
      },
      {
        "x": 47,
        "y": 40
      },
      {
        "x": 45,
        "y": 45
      },
      {
        "x": 43,
        "y": 48
      },
      {
        "x": 42,
        "y": 48
      },
      {
        "x": 42,
        "y": 48
      },
      {
        "x": 42,
        "y": 48
      }
    ],
    [
      {
        "x": 31,
        "y": 16
      },
      {
        "x": 31,
        "y": 16
      },
      {
        "x": 30,
        "y": 20
      },
      {
        "x": 30,
        "y": 26
      },
      {
        "x": 30,
        "y": 30
      },
      {
        "x": 30,
        "y": 37
      },
      {
        "x": 29,
        "y": 43
      },
      {
        "x": 29,
        "y": 46
      },
      {
        "x": 28,
        "y": 50
      },
      {
        "x": 28,
        "y": 50
      },
      {
        "x": 28,
        "y": 50
      }
    ],
    [
      {
        "x": 27,
        "y": 34
      },
      {
        "x": 27,
        "y": 34
      },
      {
        "x": 26,
        "y": 34
      },
      {
        "x": 25,
        "y": 35
      },
      {
        "x": 20,
        "y": 40
      },
      {
        "x": 17,
        "y": 43
      },
      {
        "x": 15,
        "y": 45
      },
      {
        "x": 13,
        "y": 48
      },
      {
        "x": 13,
        "y": 48
      }
    ]
  ],
  "image": {
    "description": "PNG image in ARGB format even though this is just a grayscale image.",
    "data": [
      "iVBORw0KGgoAAAANSUhEUgAAAEAAAABACAYAAACqaXHeAAAABHNCSVQICAgIfAhkiAAAAe5JREFU",
      "eJztmsmOxDAIRPGo//+XPadIUeSNYilnecdWJ0AZvOAUEanyYv7YDrAxC1BrlVpzkijC1m0yIEpk",
      "kwCZI39QSnF99w99MNIpxM5sMHrPwgIgTvToOdcL3jPzIAGuDmSUgsaGJiPVAmiDRdN21Y61/Mwl",
      "0HLA4nzr2dH/aq0mEVSrwLUmIye/s53Z75b9Qcg+wDJhaUS9/hcRYVmArGXvzIodqwhFFg5DaPCZ",
      "oqG2brMVnoGW3VQAyyiOnIo42CBZNhTAI4Wz5ouzPfeNkDUIj9k6iqEA2aPHwPUwhOB9gNISJsBO",
      "aT7C5TRoAd1XeJFSAr1JcIc5BhKA7bin/dvsBLdsij4B+jJ4ZWWkPeeQVAEYvcQZ5rZ45DY3peMk",
      "wOXo3YIcEdoVnvX72cGLGEpgB+c9gLvCTyFlFfDsDa7eG6wSvhVGsiYz05YFsAZiuUFqUUpxESql",
      "H3AEz25+tFALgFx2rgSuDdKrTKgNkR2W0vTr8R3uAs4sC9CbdFr1nXkNZkWVAdpPWZB3ZePyneAB",
      "4xbIittnclnBb/OhJHPkPYEEYAUfYVctwJOCF0nuCqP1G3k4ggVg1b23XagniLJTK+zg9RcjqRmw",
      "I6/PgE8AtgNsPgHYDrD5BGA7wOYTgO0Am08AtgNsXi/AP75YCqLRpOqkAAAAAElFTkSuQmCC"
    ]
  }
}
